schemantic/__init__.py
schemantic/project.py
schemantic/schema/__init__.py
schemantic/schema/arg_type_info.py
schemantic/schema/functional.py
schemantic/schema/model.py
schemantic/schemer/__init__.py
schemantic/schemer/abstract.py
schemantic/schemer/many.py
schemantic/schemer/single.py
schemantic/utils/__init__.py
schemantic/utils/constant.py
schemantic/utils/mapping.py
schemantic-2.0.3.dist-info/LICENSE.md
schemantic-2.0.3.dist-info/METADATA
schemantic-2.0.3.dist-info/WHEEL
schemantic-2.0.3.dist-info/RECORD
