Metadata-Version: 2.1
Name: schemantic
Version: 2.0.3
Summary: Manipulate model schemas utilizing homologous, grouped, or cultured paradigms
License: BSD-4
Author: caniko
Author-email: python@rotas.mozmail.com
Requires-Python: >=3.10,<4.0
Classifier: License :: Other/Proprietary License
Classifier: Operating System :: OS Independent
Classifier: Programming Language :: Python :: 3
Classifier: Programming Language :: Python :: 3.10
Classifier: Programming Language :: Python :: 3.11
Classifier: Programming Language :: Python :: 3.12
Classifier: Programming Language :: Python :: 3.13
Classifier: Topic :: Scientific/Engineering :: Information Analysis
Classifier: Topic :: Software Development :: Libraries :: Python Modules
Provides-Extra: toml
Provides-Extra: yaml
Requires-Dist: ordered-set (>=4.1.0,<5.0.0)
Requires-Dist: pydantic (>=2.0,<3.0)
Requires-Dist: rtoml ; extra == "toml"
Requires-Dist: ruamel-yaml ; extra == "yaml"
